envia/#cliarg.py#
envia/#env_var.py#
envia/__init__.py
envia/__init__.py~
envia/cliarg.py~
envia/env.py
envia/env.py~
envia/env_var.py~
envia/errors.py
envia/errors.py~
envia/main.py~
envia/os_var.py~
envia/py.typed
envia-0.0.2.dist-info/METADATA
envia-0.0.2.dist-info/WHEEL
envia-0.0.2.dist-info/RECORD
