Metadata-Version: 2.1
Name: envia
Version: 0.0.2
Summary: Manage your app configuration using env variables
Project-URL: Repository, https://github.com/ErikDeSmedt/envia
Author-email: Erik De Smedt <contact@erikdesmedt.be>
Maintainer-email: Erik De Smedt <contact@erikdesmedt.be>
License: MIT License
Keywords: config,env
Requires-Python: >=3.7
